fcsql/FCSLexer.g4
fcsql/FCSLexer.interp
fcsql/FCSLexer.py
fcsql/FCSLexer.tokens
fcsql/FCSParser.g4
fcsql/FCSParser.interp
fcsql/FCSParser.py
fcsql/FCSParser.tokens
fcsql/FCSParserListener.py
fcsql/__init__.py
fcsql/parser.py
fcsql/py.typed
fcs_ql_parser-1.0.1.dist-info/METADATA
fcs_ql_parser-1.0.1.dist-info/WHEEL
fcs_ql_parser-1.0.1.dist-info/top_level.txt
fcs_ql_parser-1.0.1.dist-info/zip-safe
fcs_ql_parser-1.0.1.dist-info/RECORD
